{"is_source_file": false, "format": "", "description": "", "external_files": [], "external_methods": [], "published": [], "classes": [], "methods": [], "calls": [], "search-terms": [], "state": 2, "file_id": 9, "knowledge_revision": 25, "git_revision": "b7d4d09f1ddcc5eb41db4253b60e1671c41b8ef7", "hash": "c943f83c5c83b9b7adf2bae69cf658ea", "format-version": 4, "code-base-name": "web_frontend", "filename": "web_frontend/src/app/app.component.html", "revision_history": [{"25": "b7d4d09f1ddcc5eb41db4253b60e1671c41b8ef7"}]}